skelvis/__init__.py
skelvis/jointset.py
skelvis/loss.py
skelvis/objects.py
skelvis/visualizer.py
skelvis-0.165.dist-info/LICENSE
skelvis-0.165.dist-info/METADATA
skelvis-0.165.dist-info/WHEEL
skelvis-0.165.dist-info/top_level.txt
skelvis-0.165.dist-info/RECORD
