Metadata-Version: 2.1
Name: skelvis
Version: 0.165
Summary: 3D skeleton visualizer package
Home-page: https://github.com/ScarryBear77/skelvis
Author: Peter Kovacs
Author-email: petersmith77.sb@gmail.com
License: UNKNOWN
Platform: UNKNOWN
Classifier: Programming Language :: Python :: 3
Classifier: License :: OSI Approved :: MIT License
Classifier: Operating System :: OS Independent
Requires-Dist: k3d
